pcloadletter/__init__.py
pcloadletter/__main__.py
pcloadletter/generate.py
pcloadletter/parse.py
pcloadletter-0.3.2.dist-info/entry_points.txt
pcloadletter-0.3.2.dist-info/LICENSE
pcloadletter-0.3.2.dist-info/WHEEL
pcloadletter-0.3.2.dist-info/METADATA
pcloadletter-0.3.2.dist-info/RECORD
