Metadata-Version: 2.1
Name: pcloadletter
Version: 0.3.2
Summary: PC load letter
Home-page: https://github.com/wadevries/pcloadletter
Author: Wouter de Vries
Author-email: wouter@oxyzen.nl
Classifier: License :: OSI Approved :: MIT License
Requires-Dist: WeasyPrint~=52.0
Requires-Dist: Jinja2~=2.11.3
Requires-Dist: MarkupSafe~=2.0.1
Requires-Dist: PyYAML~=5.4.1
